_quickjs.cp312-win_amd64.pyd
quickjs_runtime\repl.py
quickjs_runtime\require.py
quickjs_runtime\__init__.py
quickjs_runtime\__main__.py
quickjs_runtime-0.2.4.dist-info/METADATA
quickjs_runtime-0.2.4.dist-info/WHEEL
quickjs_runtime-0.2.4.dist-info/RECORD
