Metadata-Version: 2.1
Name: quickjs-runtime
Version: 0.2.4
Summary: Python bindings for QuickJS
Home-page: https://github.com/jrialland/python-quickjs-runtime
Author: Julien Rialland
Author-Email: julien.rialland@gmail.com
Maintainer: Julien Rialland
Maintainer-Email: julien.rialland@gmail.com
License: MIT
Project-URL: Repository, https://github.com/jrialland/python-quickjs-runtime
Project-URL: Issues, https://github.com/jrialland/python-quickjs-runtime/issues
Project-URL: Documentation, https://github.com/jrialland/python-quickjs-runtime#readme
Keywords: quickjs,javascript,js,runtime,bindings,interpreter
Classifier: Development Status :: 3 - Alpha
Classifier: Intended Audience :: Developers
Classifier: License :: OSI Approved :: MIT License
Classifier: Programming Language :: Python :: 3
Classifier: Programming Language :: Python :: 3.12
Classifier: Programming Language :: Python :: 3.13
Classifier: Programming Language :: Python :: 3.14
Classifier: Programming Language :: JavaScript
Classifier: Topic :: Software Development :: Interpreters
Classifier: Topic :: Software Development :: Libraries :: Python Modules
Requires-Python: >=3.12, <3.15
